pipe.py
only_pipe-2.0.0.dist-info/LICENSE
only_pipe-2.0.0.dist-info/METADATA
only_pipe-2.0.0.dist-info/WHEEL
only_pipe-2.0.0.dist-info/top_level.txt
only_pipe-2.0.0.dist-info/RECORD
