Metadata-Version: 2.1
Name: only-pipe
Version: 2.0.0
Summary: A non-intrusive Python pipeline.
Home-page: https://github.com/abersheeran/only-pipe
Author: abersheeran
Author-email: me@abersheeran.com
License: MIT
Platform: UNKNOWN
Classifier: License :: OSI Approved :: MIT License
Classifier: Programming Language :: Python
Classifier: Programming Language :: Python :: Implementation :: CPython
Classifier: Programming Language :: Python :: Implementation :: PyPy
